media_analyzer/__init__.py
media_analyzer/media_analyzer.py
media_analyzer/py.typed
media_analyzer/data/anaylzer_config.py
media_analyzer/data/enums/analyzer_module.py
media_analyzer/data/enums/config_types.py
media_analyzer/data/enums/face_sex.py
media_analyzer/data/enums/weather_condition.py
media_analyzer/data/interfaces/api_io.py
media_analyzer/data/interfaces/frame_data.py
media_analyzer/data/interfaces/image_data.py
media_analyzer/data/interfaces/location_types.py
media_analyzer/data/interfaces/ml_types.py
media_analyzer/machine_learning/utils.py
media_analyzer/machine_learning/caption/blip_captioner.py
media_analyzer/machine_learning/caption/captioner_protocol.py
media_analyzer/machine_learning/caption/get_captioner.py
media_analyzer/machine_learning/caption/instruct_blip_captioner.py
media_analyzer/machine_learning/caption/llm_captioner.py
media_analyzer/machine_learning/embedding/embedder_protocol.py
media_analyzer/machine_learning/embedding/get_embedder.py
media_analyzer/machine_learning/embedding/open_clip_embedder.py
media_analyzer/machine_learning/embedding/zero_clip_embedder.py
media_analyzer/machine_learning/facial_recognition/facial_recognition_protocol.py
media_analyzer/machine_learning/facial_recognition/insight_facial_recognition.py
media_analyzer/machine_learning/object_detection/object_detection_protocol.py
media_analyzer/machine_learning/object_detection/resnet_object_detection.py
media_analyzer/machine_learning/ocr/ocr_protocol.py
media_analyzer/machine_learning/ocr/resnet_tesseract_ocr.py
media_analyzer/machine_learning/visual_llm/base_visual_llm.py
media_analyzer/machine_learning/visual_llm/get_llm.py
media_analyzer/machine_learning/visual_llm/mini_cpm_llm.py
media_analyzer/machine_learning/visual_llm/openai_llm.py
media_analyzer/processing/process_utils.py
media_analyzer/processing/assets/scenes.json
media_analyzer/processing/pipeline/pipeline.py
media_analyzer/processing/pipeline/pipeline_module.py
media_analyzer-0.4.1.dist-info/METADATA
media_analyzer-0.4.1.dist-info/WHEEL
media_analyzer-0.4.1.dist-info/RECORD
