Metadata-Version: 2.4
Name: media-analyzer
Version: 0.4.1
Summary: Analyze video/image with machine learning methods, exif data, and other file based information. 
Project-URL: Homepage, https://github.com/RuurdBijlsma/media-analyzer
Project-URL: Repository, https://github.com/RuurdBijlsma/media-analyzer
Project-URL: Documentation, https://ruurdbijlsma.github.io/media-analyzer
Author-email: Ruurd Bijlsma <ruurd@bijlsma.dev>
License-Expression: MIT
Requires-Python: <3.13,>=3.10
Requires-Dist: accelerate>=1.3.0
Requires-Dist: bitsandbytes>=0.45.0
Requires-Dist: hf-xet>=1.1.10
Requires-Dist: insightface>=0.7.3
Requires-Dist: material-color-utilities>=0.2.0
Requires-Dist: meteostat>=1.6.8
Requires-Dist: networkx>=3.4.2
Requires-Dist: onnxruntime-gpu>=1.20.1
Requires-Dist: onnxruntime>=1.20.1
Requires-Dist: open-clip-torch>=3.2.0
Requires-Dist: openai>=1.59.8
Requires-Dist: opencv-python>=4.11.0.86
Requires-Dist: pillow-avif-plugin>=1.4.6
Requires-Dist: pillow>=11.1.0
Requires-Dist: pyexiftool>=0.5.6
Requires-Dist: pytesseract>=0.3.13
Requires-Dist: pytz>=2024.2
Requires-Dist: requests>=2.32.5
Requires-Dist: reverse-geocode>=1.6.5
Requires-Dist: scikit-learn>=1.6.1
Requires-Dist: scipy>=1.15.1
Requires-Dist: timezonefinder>=6.5.7
Requires-Dist: torch>=2.8.0
Requires-Dist: torchvision>=0.23.0
Requires-Dist: transformers>=4.48.0
